tdr/__init__.py
tdr/commonIDsearch.py
tdr/makedark.py
tdr/makedark_old.py
tdr/makeflat.py
tdr/mask_split.py
tdr/reduce.py
tdr/stackfits.py
tdr-0.0.1.dist-info/LICENCE
tdr-0.0.1.dist-info/METADATA
tdr-0.0.1.dist-info/WHEEL
tdr-0.0.1.dist-info/entry_points.txt
tdr-0.0.1.dist-info/top_level.txt
tdr-0.0.1.dist-info/RECORD
