Metadata-Version: 2.1
Name: tdr
Version: 0.0.1
Summary: TriCCS Data Reduction
Home-page: https://bitbucket.org/jin_beniyama/triccs-data-reduction/src/master/
Author: Jin BENIYAMA
Author-email: beniyama@ioa.s.u-tokyo.ac.jp
Maintainer: Jin BENIYAMA
Maintainer-email: beniyama@ioa.s.u-tokyo.ac.jp
License: UNKNOWN
Platform: UNKNOWN
